heirloom/__init__.py
heirloom/prompts/__init__.py
heirloom/prompts/parsing.py
heirloom-0.0.1.dist-info/WHEEL
heirloom-0.0.1.dist-info/METADATA
heirloom-0.0.1.dist-info/RECORD
