Metadata-Version: 2.3
Name: heirloom
Version: 0.0.1
Summary: A Package for Prompt Management.
Classifier: Programming Language :: Python :: 3
Classifier: Operating System :: OS Independent
Requires-Python: >=3.9
Project-URL: Homepage, https://github.com/hexsyw/heirloom
